tsdlr-0.3.0.dist-info/METADATA
tsdlr-0.3.0.dist-info/WHEEL
tsdlr-0.3.0.dist-info/license_files/LICENSE
tsdlr/tsdlr.pyi
tsdlr/__init__.py
tsdlr/py.typed
tsdlr/tsdlr.pypy310-pp73-x86_64-linux-gnu.so
tsdlr-0.3.0.dist-info/RECORD
