Metadata-Version: 2.1
Name: tsdlr
Version: 0.3.0
Classifier: Programming Language :: Rust
Classifier: Programming Language :: Python :: Implementation :: CPython
Classifier: Programming Language :: Python :: Implementation :: PyPy
Requires-Dist: numpy
Requires-Dist: pre-commit ; extra == 'dev'
Requires-Dist: bump2version ; extra == 'dev'
Requires-Dist: pytest ; extra == 'dev'
Requires-Dist: pytest-xdist ; extra == 'dev'
Requires-Dist: pytest-cov ; extra == 'dev'
Requires-Dist: pytest-sugar ; extra == 'dev'
Requires-Dist: streamlit ; extra == 'dev'
Requires-Dist: seaborn ; extra == 'dev'
Requires-Dist: plotly ; extra == 'dev'
Requires-Dist: scipy ; extra == 'dev'
Provides-Extra: dev
License-File: LICENSE
Requires-Python: >=3.9
